proompt/__init__.py
proompt/data.py
proompt/base/__init__.py
proompt/base/context.py
proompt/base/prompt.py
proompt/base/provider.py
proompt-0.2.1.dist-info/licenses/LICENSE
proompt-0.2.1.dist-info/METADATA
proompt-0.2.1.dist-info/WHEEL
proompt-0.2.1.dist-info/top_level.txt
proompt-0.2.1.dist-info/RECORD
