Metadata-Version: 2.4
Name: proompt
Version: 0.2.1
Summary: Object-oriented prompting for Python
Author: Burhan Qaddoumi
Maintainer: https://github.com/Burhan-Q
Project-URL: homepage, https://github.com/Burhan-Q/proompt
Project-URL: source, https://github.com/Burhan-Q/proompt
Project-URL: issues, https://github.com/Burhan-Q/proompt/issues
Keywords: ai,prompting,prompts,object oriented,ai agent,prompt toolkit,devtools,developer tools,llm,prompt,code tools,structure
Requires-Python: >=3.12
License-File: LICENSE
Requires-Dist: pydantic>=2.11.9
Requires-Dist: pydantic-ai-slim>=1.11.0
Provides-Extra: dev
Requires-Dist: pylint>=3.3.8; extra == "dev"
Requires-Dist: pytest>=8.4.2; extra == "dev"
Requires-Dist: ruff>=0.13.2; extra == "dev"
Requires-Dist: pytest-cov; extra == "dev"
Dynamic: license-file
